{
  "Overview": {
    "Id": 4751124,
    "ExtId": "8049B232-A0E2-4A56-80F8-A3878CE9C14B",
    "Title": "Business without Debate",
    "HRSTag": "hs_2BusinessWODebate",
    "Date": "2024-11-06T00:00:00",
    "Location": "Commons Chamber",
    "House": "Commons",
    "Source": 2,
    "VolumeNo": 756,
    "ContentLastUpdated": "2024-11-08T13:16:27.527",
    "DebateTypeId": 1,
    "SectionType": 1,
    "NextDebateExtId": "A0C48801-FB41-4944-9BD3-DF518ECC1C1C",
    "NextDebateTitle": " Road Fuel Market",
    "PreviousDebateExtId": "DBE9C141-29E1-4666-B0D1-CF616C409D66",
    "PreviousDebateTitle": "Budget Resolutions"
  },
  "Navigator": [
    {
      "Id": 4751104,
      "Title": "Commons Chamber",
      "ParentId": null,
      "SortOrder": 1,
      "ExternalId": "90970f9c-e65c-4a47-9a92-02f47570c169",
      "HRSTag": null,
      "HansardSection": null,
      "Timecode": null
    },
    {
      "Id": 4751124,
      "Title": "Business without Debate",
      "ParentId": 4751104,
      "SortOrder": 21,
      "ExternalId": "8049B232-A0E2-4A56-80F8-A3878CE9C14B",
      "HRSTag": "hs_2BusinessWODebate",
      "HansardSection": "DX-DZ",
      "Timecode": null
    }
  ],
  "Items": [
    {
      "ItemType": "Contribution",
      "ItemId": 40890765,
      "MemberId": null,
      "AttributedTo": null,
      "Value": "Delegated Legislation",
      "OrderInSection": 1,
      "Timecode": null,
      "ExternalId": "FCAEBA9A-BB47-4C83-A17F-B3F65E620DFB",
      "HRSTag": "hs_6bFormalmotion",
      "HansardSection": "DX-DZ",
      "UIN": null,
      "IsReiteration": false
    },
    {
      "ItemType": "Contribution",
      "ItemId": 40890766,
      "MemberId": null,
      "AttributedTo": null,
      "Value": "<em>Motion made, and Question put forthwith (Standing Order No. 118(6),</em>",
      "OrderInSection": 2,
      "Timecode": null,
      "ExternalId": "24110674001483",
      "HRSTag": "hs_Para",
      "HansardSection": "DX-DZ",
      "UIN": null,
      "IsReiteration": false
    },
    {
      "ItemType": "Contribution",
      "ItemId": 40890767,
      "MemberId": null,
      "AttributedTo": null,
      "Value": "<span id=\"473\" class=\"column-number column-only\" data-column-number=\"473\"></span>",
      "OrderInSection": 3,
      "Timecode": null,
      "ExternalId": null,
      "HRSTag": "hs_ColumnNumber",
      "HansardSection": null,
      "UIN": null,
      "IsReiteration": false
    },
    {
      "ItemType": "Contribution",
      "ItemId": 40890768,
      "MemberId": null,
      "AttributedTo": null,
      "Value": "Constitutional Law",
      "OrderInSection": 5,
      "Timecode": null,
      "ExternalId": "B9FE96D3-58CD-4BCF-8C32-935D429A7C2A",
      "HRSTag": "hs_7SmCapsHdg",
      "HansardSection": "DX-DZ",
      "UIN": null,
      "IsReiteration": false
    },
    {
      "ItemType": "Contribution",
      "ItemId": 40890769,
      "MemberId": null,
      "AttributedTo": null,
      "Value": "That the draft Scotland Act 1998 (Specification of Devolved Tax) (Building Safety) Order 2024, which was laid before this House on 10 September, be approved.<em>—(Christian Wakeford.)</em>",
      "OrderInSection": 6,
      "Timecode": null,
      "ExternalId": "24110674001493",
      "HRSTag": "hs_brev",
      "HansardSection": "DX-DZ",
      "UIN": null,
      "IsReiteration": false
    },
    {
      "ItemType": "Contribution",
      "ItemId": 40890770,
      "MemberId": null,
      "AttributedTo": null,
      "Value": "<em>Question agreed to.</em>",
      "OrderInSection": 7,
      "Timecode": null,
      "ExternalId": "24110674001484",
      "HRSTag": "hs_Para",
      "HansardSection": "DX-DZ",
      "UIN": null,
      "IsReiteration": false
    },
    {
      "ItemType": "Contribution",
      "ItemId": 40890771,
      "MemberId": null,
      "AttributedTo": null,
      "Value": "<em>Motion made, and Question put forthwith (Standing Order No. 118(6),</em>",
      "OrderInSection": 8,
      "Timecode": null,
      "ExternalId": "24110674001485",
      "HRSTag": "hs_Para",
      "HansardSection": "DX-DZ",
      "UIN": null,
      "IsReiteration": false
    },
    {
      "ItemType": "Contribution",
      "ItemId": 40890772,
      "MemberId": null,
      "AttributedTo": null,
      "Value": "Immigration",
      "OrderInSection": 9,
      "Timecode": null,
      "ExternalId": "4CF8BC8C-E04A-4843-9E97-9F1B1E3BF707",
      "HRSTag": "hs_7SmCapsHdg",
      "HansardSection": "DX-DZ",
      "UIN": null,
      "IsReiteration": false
    },
    {
      "ItemType": "Contribution",
      "ItemId": 40890773,
      "MemberId": null,
      "AttributedTo": null,
      "Value": "That the draft Immigration and Nationality (Fees) (Amendment) Order 2024, which was laid before this House on 12 September, be approved.<em>—(Christian Wakeford.)</em>",
      "OrderInSection": 10,
      "Timecode": null,
      "ExternalId": "24110674001494",
      "HRSTag": "hs_brev",
      "HansardSection": "DX-DZ",
      "UIN": null,
      "IsReiteration": false
    },
    {
      "ItemType": "Contribution",
      "ItemId": 40890774,
      "MemberId": null,
      "AttributedTo": null,
      "Value": "<em>Question agreed to.</em>",
      "OrderInSection": 11,
      "Timecode": null,
      "ExternalId": "24110674001486",
      "HRSTag": "hs_Para",
      "HansardSection": "DX-DZ",
      "UIN": null,
      "IsReiteration": false
    },
    {
      "ItemType": "Contribution",
      "ItemId": 40890775,
      "MemberId": null,
      "AttributedTo": null,
      "Value": "<em>Motion made, and Question put forthwith (Standing Order No. 118(6),</em>",
      "OrderInSection": 12,
      "Timecode": null,
      "ExternalId": "24110674001487",
      "HRSTag": "hs_Para",
      "HansardSection": "DX-DZ",
      "UIN": null,
      "IsReiteration": false
    },
    {
      "ItemType": "Contribution",
      "ItemId": 40890776,
      "MemberId": null,
      "AttributedTo": null,
      "Value": "Animals",
      "OrderInSection": 13,
      "Timecode": null,
      "ExternalId": "F00DEE65-563B-409D-99E5-7889C7E317FA",
      "HRSTag": "hs_7SmCapsHdg",
      "HansardSection": "DX-DZ",
      "UIN": null,
      "IsReiteration": false
    },
    {
      "ItemType": "Contribution",
      "ItemId": 40890777,
      "MemberId": null,
      "AttributedTo": null,
      "Value": "That the draft Animal Welfare (Livestock Exports) Enforcement Regulations 2024, which were laid before this House on 12 September, be approved.<em>—(Christian Wakeford.)</em>",
      "OrderInSection": 14,
      "Timecode": null,
      "ExternalId": "24110674001495",
      "HRSTag": "hs_brev",
      "HansardSection": "DX-DZ",
      "UIN": null,
      "IsReiteration": false
    },
    {
      "ItemType": "Contribution",
      "ItemId": 40890778,
      "MemberId": null,
      "AttributedTo": null,
      "Value": "<em>Question agreed to</em><em>.</em>",
      "OrderInSection": 15,
      "Timecode": null,
      "ExternalId": "24110674001488",
      "HRSTag": "hs_Para",
      "HansardSection": "DX-DZ",
      "UIN": null,
      "IsReiteration": false
    },
    {
      "ItemType": "Contribution",
      "ItemId": 40890779,
      "MemberId": null,
      "AttributedTo": null,
      "Value": "<em>Motion made, and Question put forthwith (Standing Order No. 118(6),</em>",
      "OrderInSection": 16,
      "Timecode": null,
      "ExternalId": "24110674001489",
      "HRSTag": "hs_Para",
      "HansardSection": "DX-DZ",
      "UIN": null,
      "IsReiteration": false
    },
    {
      "ItemType": "Contribution",
      "ItemId": 40890780,
      "MemberId": null,
      "AttributedTo": null,
      "Value": "Electronic Communications",
      "OrderInSection": 17,
      "Timecode": null,
      "ExternalId": "13ACAC0E-6FE1-41E4-A78C-8EE72AF9BFE4",
      "HRSTag": "hs_7SmCapsHdg",
      "HansardSection": "DX-DZ",
      "UIN": null,
      "IsReiteration": false
    },
    {
      "ItemType": "Contribution",
      "ItemId": 40890781,
      "MemberId": null,
      "AttributedTo": null,
      "Value": "That the draft Online Safety Act 2023 (Priority Offences) (Amendment) Regulations 2024, which were laid before this House on 12 September, be approved.<em>—(Christian Wakeford.)</em>",
      "OrderInSection": 18,
      "Timecode": null,
      "ExternalId": "24110674001496",
      "HRSTag": "hs_brev",
      "HansardSection": "DX-DZ",
      "UIN": null,
      "IsReiteration": false
    },
    {
      "ItemType": "Contribution",
      "ItemId": 40890782,
      "MemberId": null,
      "AttributedTo": null,
      "Value": "<em>Question agreed to.</em>",
      "OrderInSection": 19,
      "Timecode": null,
      "ExternalId": "24110674001490",
      "HRSTag": "hs_Para",
      "HansardSection": "DX-DZ",
      "UIN": null,
      "IsReiteration": false
    },
    {
      "ItemType": "Contribution",
      "ItemId": 40890783,
      "MemberId": null,
      "AttributedTo": null,
      "Value": "<em>Motion made, and Question put forthwith (Standing Order No. 118(6),</em>",
      "OrderInSection": 20,
      "Timecode": null,
      "ExternalId": "24110674001491",
      "HRSTag": "hs_Para",
      "HansardSection": "DX-DZ",
      "UIN": null,
      "IsReiteration": false
    },
    {
      "ItemType": "Contribution",
      "ItemId": 40890784,
      "MemberId": null,
      "AttributedTo": null,
      "Value": "Public Passenger Transport",
      "OrderInSection": 21,
      "Timecode": null,
      "ExternalId": "6BE06692-5FFF-40DF-B239-97C4C8D71F38",
      "HRSTag": "hs_7Bill",
      "HansardSection": "DX-DZ",
      "UIN": null,
      "IsReiteration": false
    },
    {
      "ItemType": "Contribution",
      "ItemId": 40890785,
      "MemberId": null,
      "AttributedTo": null,
      "Value": "That the draft Franchising Schemes (Franchising Authorities) (England) Regulations 2024, which were laid before this House on 9 September, be approved.<em>—(Christian Wakeford.)</em>",
      "OrderInSection": 22,
      "Timecode": null,
      "ExternalId": "24110674001497",
      "HRSTag": "hs_brev",
      "HansardSection": "DX-DZ",
      "UIN": null,
      "IsReiteration": false
    },
    {
      "ItemType": "Contribution",
      "ItemId": 40890786,
      "MemberId": null,
      "AttributedTo": null,
      "Value": "<em>Question agreed to.</em>",
      "OrderInSection": 23,
      "Timecode": null,
      "ExternalId": "24110674001492",
      "HRSTag": "hs_Para",
      "HansardSection": "DX-DZ",
      "UIN": null,
      "IsReiteration": false
    }
  ],
  "ChildDebates": []
}